README.rst
setup.py
dotenvfile/__init__.py
dotenvfile/version.txt
dotenvfile.egg-info/PKG-INFO
dotenvfile.egg-info/SOURCES.txt
dotenvfile.egg-info/dependency_links.txt
dotenvfile.egg-info/top_level.txt