Metadata-Version: 1.1
Name: dotenvfile
Version: 0.1.0
Summary: .env file parser
Home-page: https://github.com/smartmob-project/dotenvfile
Author: Andre Caron
Author-email: ac@smartmob.org
License: UNKNOWN
Platform: UNKNOWN
Classifier: Development Status :: 1 - Planning
Classifier: Intended Audience :: Developers
Classifier: License :: OSI Approved :: MIT License
Classifier: Operating System :: MacOS :: MacOS X
Classifier: Programming Language :: Python
Classifier: Programming Language :: Python :: 3.5
Classifier: Topic :: Software Development :: Libraries
